PrintMsg/Main.py
PrintMsg/utils.py
PrintMsg-1.0.1.dist-info/LICENSE
PrintMsg-1.0.1.dist-info/METADATA
PrintMsg-1.0.1.dist-info/WHEEL
PrintMsg-1.0.1.dist-info/top_level.txt
PrintMsg-1.0.1.dist-info/RECORD
